{
  "width": 909,
  "height": 800,
  "cx": [
    [ "Author", 387 ],
    [ "write", 501 ],
    [ "Episode", 628 ],
    [ "Have", 755 ],
    [ "Season", 855 ],
    [ "Question", 81 ],
    [ "propose", 501 ],
    [ "belong to", 628 ],
    [ "Contain", 81 ],
    [ "Quizz", 185 ],
    [ "Play", 280 ],
    [ "User", 387 ],
    [ "favorite", 501 ],
    [ "Quote", 628 ],
    [ "Avatar", 280 ],
    [ "choice", 387 ],
    [ "rate", 501 ],
    [ "say", 628 ],
    [ "Personage", 628 ],
    [ "be", 628 ],
    [ "Actor", 628 ]
  ],
  "cy": [
    [ "Author", 51 ],
    [ "write", 51 ],
    [ "Episode", 51 ],
    [ "Have", 51 ],
    [ "Season", 51 ],
    [ "Question", 152 ],
    [ "propose", 152 ],
    [ "belong to", 152 ],
    [ "Contain", 287 ],
    [ "Quizz", 287 ],
    [ "Play", 287 ],
    [ "User", 287 ],
    [ "favorite", 287 ],
    [ "Quote", 287 ],
    [ "Avatar", 405 ],
    [ "choice", 405 ],
    [ "rate", 405 ],
    [ "say", 405 ],
    [ "Personage", 514 ],
    [ "be", 623 ],
    [ "Actor", 732 ]
  ],
  "shift": [
    [ "write,Author,0", 0 ],
    [ "write,Episode,0", 0 ],
    [ "Have,Season,0", 0 ],
    [ "Have,Episode,0", 0 ],
    [ "propose,User,0", 0 ],
    [ "propose,Quote,0", 0 ],
    [ "belong to,Episode,0", 0 ],
    [ "belong to,Quote,0", 0 ],
    [ "Contain,Quizz,0", 0 ],
    [ "Contain,Question,0", 0 ],
    [ "Play,Quizz,0", 0 ],
    [ "Play,User,0", 0 ],
    [ "favorite,User,0", 0 ],
    [ "favorite,Quote,0", 0 ],
    [ "choice,User,0", 0 ],
    [ "choice,Avatar,0", 0 ],
    [ "rate,User,0", 0 ],
    [ "rate,Quote,0", 0 ],
    [ "say,Quote,0", 0 ],
    [ "say,Personage,0", 0 ],
    [ "be,Actor,0", 0 ],
    [ "be,Personage,0", 0 ]
  ],
  "ratio": []
}